README.md
setup.py
cccrontab/__init__.py
cccrontab/__main__.py
cccrontab.egg-info/PKG-INFO
cccrontab.egg-info/SOURCES.txt
cccrontab.egg-info/dependency_links.txt
cccrontab.egg-info/not-zip-safe
cccrontab.egg-info/top_level.txt